backends/__init__.py
backends/filesystem/__init__.py
backends/filesystem/async.py
backends/filesystem/sync.py
integrations/__init__.py
integrations/mongo.py
integrations/sqlalchemy.py
integrations/tortoise.py
storage_hub-0.0.10.dist-info/METADATA
storage_hub-0.0.10.dist-info/WHEEL
storage_hub-0.0.10.dist-info/top_level.txt
storage_hub-0.0.10.dist-info/RECORD
