Metadata-Version: 2.1
Name: storage-hub
Version: 0.0.10
Summary: soon
Home-page: https://github.com/VitailOG/storage-hub
Author: Vitaliy Zakharkiv
Author-email: vzaharkiv28@mail.com
License: MIT
Keywords: pypi,cicd,python
Classifier: Development Status :: 1 - Planning
Classifier: Intended Audience :: Developers
Classifier: Programming Language :: Python :: 3
Classifier: Operating System :: Unix
Classifier: Operating System :: MacOS :: MacOS X
Classifier: Operating System :: Microsoft :: Windows
